{"errors":[],"warnings":[],"namedChunkGroups":{"polyfill":{"chunks":[0,4],"assets":["webpack-runtime-03238d75afcc9949d033.js","webpack-runtime-03238d75afcc9949d033.js.map","polyfill-effd73b44186fe897d74.js","polyfill-effd73b44186fe897d74.js.map"],"children":{},"childAssets":{}},"app":{"chunks":[0,5,3,1],"assets":["webpack-runtime-03238d75afcc9949d033.js","webpack-runtime-03238d75afcc9949d033.js.map","styles.2186413952e4850e3f97.css","styles-29163f9dced6fe4a408a.js","styles-29163f9dced6fe4a408a.js.map","framework-2e650e46695fe483e136.js","framework-2e650e46695fe483e136.js.map","app-1627cfaf05cd8bc03815.js","app-1627cfaf05cd8bc03815.js.map"],"children":{},"childAssets":{}},"component---src-pages-index-js":{"chunks":[2],"assets":["component---src-pages-index-js-0f79f0c4eb87fced07eb.js","component---src-pages-index-js-0f79f0c4eb87fced07eb.js.map"],"children":{},"childAssets":{}}},"assetsByChunkName":{"polyfill":["webpack-runtime-03238d75afcc9949d033.js","polyfill-effd73b44186fe897d74.js"],"app":["webpack-runtime-03238d75afcc9949d033.js","styles.2186413952e4850e3f97.css","styles-29163f9dced6fe4a408a.js","framework-2e650e46695fe483e136.js","app-1627cfaf05cd8bc03815.js"],"component---src-pages-index-js":["component---src-pages-index-js-0f79f0c4eb87fced07eb.js"]}}